{"blue":{"background_color":"#1a61ab","bg_color":"#FFFFFF","text_color":"#ffffff","link_color":"#ccdef0","link_hover_color":"#ffffff","title":"Blue","class":"blue","type":"default"},"gray":{"background_color":"#f8f9fa","bg_color":"#FFFFFF","text_color":"","link_color":"","link_hover_color":"","title":"Gray","class":"gray","type":"default"},"dark":{"background_color":"#23252f","bg_color":"#FFFFFF","text_color":"#6c757d","link_color":"#6c757d","link_hover_color":"#ffffff","title":"Dark","class":"dark","type":"default"},"dark_blue_1":{"background_color":"#233442","bg_color":"#FFFFFF","text_color":"#bbc8d3","link_color":"#bbc8d3","link_hover_color":"#ffffff","title":"Dark Blue 1","class":"dark_blue_1","type":"default"},"dark_blue_2":{"background_color":"#1a2835","bg_color":"#FFFFFF","text_color":"#dce4ed","link_color":"#889aac","link_hover_color":"#ffffff","title":"Dark Blue 2","class":"dark_blue_2","type":"default"}}