{"body_bg":{"class":"body_bg","name":"Heading","color":"#2b2b32"},"text":{"name":"Text","class":"text","color":"#6c757d"},"link_hover":{"name":"Link hover","class":"link_hover","color":"#0056b3"},"palett_1_bg":{"class":"palett_1_bg","name":"Highlight bg","color":"#1a61ab"},"gray-500":{"name":"Gray-500","color":"#858a9e","class":"gray-500"},"gray-600":{"name":"Gray-600","color":"#6e7489","class":"gray-600"},"gray-700":{"name":"Gray-700","color":"#585e73","class":"gray-700"},"gray-800":{"name":"Gray-800","color":"#444a5e","class":"gray-800"},"gray-900":{"name":"Gray-900","color":"#323748","class":"gray-900"}}